{
  "content": [
    {
      "content": null,
      "created": "2023-07-30T01:07:06.603586Z",
      "format": null,
      "last_modified": "2023-07-30T01:06:45.451230Z",
      "mimetype": null,
      "name": "data-science-python-math.ipynb",
      "path": "data-science-python-math.ipynb",
      "size": 24796,
      "type": "notebook",
      "writable": true
    },
    {
      "content": null,
      "created": "2023-07-30T01:07:06.603586Z",
      "format": null,
      "last_modified": "2023-07-30T01:06:45.463230Z",
      "mimetype": null,
      "name": "data-science-python-plotting.ipynb",
      "path": "data-science-python-plotting.ipynb",
      "size": 140836,
      "type": "notebook",
      "writable": true
    },
    {
      "content": null,
      "created": "2023-07-30T01:07:06.599586Z",
      "format": null,
      "last_modified": "2023-07-30T01:06:45.431230Z",
      "mimetype": null,
      "name": "data-science-python-advanced-np-pd.ipynb",
      "path": "data-science-python-advanced-np-pd.ipynb",
      "size": 110620,
      "type": "notebook",
      "writable": true
    },
    {
      "content": null,
      "created": "2023-07-30T01:07:06.607586Z",
      "format": null,
      "last_modified": "2023-07-30T01:06:45.487231Z",
      "mimetype": null,
      "name": "data-science-python-types.ipynb",
      "path": "data-science-python-types.ipynb",
      "size": 26757,
      "type": "notebook",
      "writable": true
    },
    {
      "content": null,
      "created": "2023-07-30T01:07:06.603586Z",
      "format": null,
      "last_modified": "2023-07-30T01:06:45.455230Z",
      "mimetype": null,
      "name": "data-science-python-multiprocessing.ipynb",
      "path": "data-science-python-multiprocessing.ipynb",
      "size": 43480,
      "type": "notebook",
      "writable": true
    },
    {
      "content": null,
      "created": "2023-07-30T01:07:06.599586Z",
      "format": null,
      "last_modified": "2023-07-30T01:06:45.435230Z",
      "mimetype": null,
      "name": "data-science-python-basics-recap.ipynb",
      "path": "data-science-python-basics-recap.ipynb",
      "size": 30227,
      "type": "notebook",
      "writable": true
    },
    {
      "content": null,
      "created": "2023-07-30T01:07:06.603586Z",
      "format": null,
      "last_modified": "2023-07-30T01:06:45.443230Z",
      "mimetype": null,
      "name": "data-science-python-functions.ipynb",
      "path": "data-science-python-functions.ipynb",
      "size": 35215,
      "type": "notebook",
      "writable": true
    },
    {
      "content": null,
      "created": "2023-07-30T01:07:06.599586Z",
      "format": null,
      "last_modified": "2023-07-30T01:06:45.439230Z",
      "mimetype": null,
      "name": "data-science-python-files.ipynb",
      "path": "data-science-python-files.ipynb",
      "size": 39960,
      "type": "notebook",
      "writable": true
    },
    {
      "content": null,
      "created": "2023-07-30T01:07:06.599586Z",
      "format": null,
      "last_modified": "2023-07-30T01:06:45.435230Z",
      "mimetype": null,
      "name": "data-science-python-exceptions.ipynb",
      "path": "data-science-python-exceptions.ipynb",
      "size": 11661,
      "type": "notebook",
      "writable": true
    },
    {
      "content": null,
      "created": "2023-07-30T01:07:06.603586Z",
      "format": null,
      "last_modified": "2023-07-30T01:06:45.439230Z",
      "mimetype": null,
      "name": "data-science-python-flow.ipynb",
      "path": "data-science-python-flow.ipynb",
      "size": 38931,
      "type": "notebook",
      "writable": true
    },
    {
      "content": null,
      "created": "2023-07-30T01:07:06.603586Z",
      "format": null,
      "last_modified": "2023-07-30T01:06:45.447230Z",
      "mimetype": null,
      "name": "data-science-python-iterables.ipynb",
      "path": "data-science-python-iterables.ipynb",
      "size": 63418,
      "type": "notebook",
      "writable": true
    },
    {
      "content": null,
      "created": "2023-07-30T01:07:06.603586Z",
      "format": null,
      "last_modified": "2023-07-30T01:06:45.451230Z",
      "mimetype": null,
      "name": "data-science-python-loops.ipynb",
      "path": "data-science-python-loops.ipynb",
      "size": 39896,
      "type": "notebook",
      "writable": true
    },
    {
      "content": null,
      "created": "2023-07-30T01:07:06.607586Z",
      "format": null,
      "last_modified": "2023-07-30T01:06:45.495231Z",
      "mimetype": null,
      "name": "data-science-python-typing.ipynb",
      "path": "data-science-python-typing.ipynb",
      "size": 130482,
      "type": "notebook",
      "writable": true
    },
    {
      "content": null,
      "created": "2023-07-30T01:07:06.607586Z",
      "format": null,
      "last_modified": "2023-07-30T01:06:45.479231Z",
      "mimetype": null,
      "name": "data-science-python-testing.ipynb",
      "path": "data-science-python-testing.ipynb",
      "size": 21873,
      "type": "notebook",
      "writable": true
    },
    {
      "content": null,
      "created": "2023-07-30T01:07:06.603586Z",
      "format": null,
      "last_modified": "2023-07-30T01:06:45.443230Z",
      "mimetype": null,
      "name": "data-science-python-glob.ipynb",
      "path": "data-science-python-glob.ipynb",
      "size": 9040,
      "type": "notebook",
      "writable": true
    },
    {
      "content": null,
      "created": "2023-07-30T01:07:06.599586Z",
      "format": null,
      "last_modified": "2023-07-30T01:06:45.435230Z",
      "mimetype": null,
      "name": "data-science-python-basics.ipynb",
      "path": "data-science-python-basics.ipynb",
      "size": 150417,
      "type": "notebook",
      "writable": true
    },
    {
      "content": null,
      "created": "2023-07-30T01:07:06.607586Z",
      "format": null,
      "last_modified": "2023-07-30T01:06:45.471231Z",
      "mimetype": null,
      "name": "data-science-python-subprocess.ipynb",
      "path": "data-science-python-subprocess.ipynb",
      "size": 21514,
      "type": "notebook",
      "writable": true
    }
  ],
  "created": "2023-07-30T01:07:06.607586Z",
  "format": "json",
  "last_modified": "2023-07-30T01:07:06.607586Z",
  "mimetype": null,
  "name": "",
  "path": "",
  "size": null,
  "type": "directory",
  "writable": true
}